omegalul/__init__.py
omegalul-1.0.3.dist-info/METADATA
omegalul-1.0.3.dist-info/WHEEL
omegalul-1.0.3.dist-info/top_level.txt
omegalul-1.0.3.dist-info/RECORD
