Metadata-Version: 2.1
Name: omegalul
Version: 1.0.3
Summary: A Python library for building omegle clients
Home-page: https://github.com/pcranaway/omegalul
Author: pcranaway
Author-email: pcranaway@tuta.io
License: UNKNOWN
Platform: UNKNOWN
Requires-Dist: requests
